[
  {
    "prefab": "MWL_blacksmithStone_tier1",
    "stack": 1,
    "price": 500,
    "requiredGlobalKey": "defeated_gdking"
  },
  {
    "prefab": "SwordBronze",
    "stack": 1,
    "price": 300,
    "requiredGlobalKey": "defeated_gdking"
  },
  {
    "prefab": "AxeBronze",
    "stack": 1,
    "price": 250,
    "requiredGlobalKey": "defeated_gdking"
  },
  {
    "prefab": "MaceBronze",
    "stack": 1,
    "price": 280,
    "requiredGlobalKey": "defeated_gdking"
  },
  {
    "prefab": "AtgeirBronze",
    "stack": 1,
    "price": 350,
    "requiredGlobalKey": "defeated_gdking"
  },
  {
    "prefab": "KnifeBronze",
    "stack": 1,
    "price": 200,
    "requiredGlobalKey": "defeated_gdking"
  },
  {
    "prefab": "SpearBronze",
    "stack": 1,
    "price": 220,
    "requiredGlobalKey": "defeated_gdking"
  },
  {
    "prefab": "ArmorBronzeChest",
    "stack": 1,
    "price": 400,
    "requiredGlobalKey": "defeated_gdking"
  },
  {
    "prefab": "ArmorBronzeLegs",
    "stack": 1,
    "price": 350,
    "requiredGlobalKey": "defeated_gdking"
  },
  {
    "prefab": "HelmetBronze",
    "stack": 1,
    "price": 300,
    "requiredGlobalKey": "defeated_gdking"
  },
  {
    "prefab": "ShieldBronzeBuckler",
    "stack": 1,
    "price": 250,
    "requiredGlobalKey": "defeated_gdking"
  },
  {
    "prefab": "CrossbowBronze",
    "stack": 1,
    "price": 450,
    "requiredGlobalKey": "defeated_gdking"
  },
  {
    "prefab": "ArrowBronze",
    "stack": 20,
    "price": 100,
    "requiredGlobalKey": "defeated_gdking"
  },
  {
    "prefab": "BoltBronze",
    "stack": 20,
    "price": 120,
    "requiredGlobalKey": "defeated_gdking"
  },
  {
    "prefab": "Bronze",
    "stack": 1,
    "price": 30,
    "requiredGlobalKey": "defeated_gdking"
  },
  {
    "prefab": "Bronze",
    "stack": 10,
    "price": 280,
    "requiredGlobalKey": "defeated_gdking"
  },
  {
    "prefab": "BronzeNails",
    "stack": 20,
    "price": 60,
    "requiredGlobalKey": "defeated_gdking"
  },
  {
    "prefab": "PickaxeBronze",
    "stack": 1,
    "price": 350,
    "requiredGlobalKey": "defeated_gdking"
  },
  {
    "prefab": "AxeBronze",
    "stack": 1,
    "price": 250,
    "requiredGlobalKey": "defeated_gdking"
  },
  {
    "prefab": "Hammer",
    "stack": 1,
    "price": 50
  },
  {
    "prefab": "Hoe",
    "stack": 1,
    "price": 80
  },
  {
    "prefab": "Cultivator",
    "stack": 1,
    "price": 150,
    "requiredGlobalKey": "defeated_gdking"
  },
  {
    "prefab": "Anvil",
    "stack": 1,
    "price": 800,
    "requiredGlobalKey": "defeated_gdking"
  },
  {
    "prefab": "BronzeScrap",
    "stack": 1,
    "price": 15,
    "requiredGlobalKey": "defeated_gdking"
  },
  {
    "prefab": "Chitin",
    "stack": 1,
    "price": 20,
    "requiredGlobalKey": "defeated_gdking"
  }
] 